yomikata/__init__.py
yomikata/__main__.py
yomikata/dbert.py
yomikata/dictionary.py
yomikata/main.py
yomikata/reader.py
yomikata/utils.py
yomikata/config/__init__.py
yomikata/config/config.py
yomikata/config/dbert-train-args.json
yomikata/config/heteronyms.json
yomikata/config/heteronyms_Sato2022.json
yomikata/download/download.py
yomikata-0.0.4.dist-info/LICENSE.md
yomikata-0.0.4.dist-info/METADATA
yomikata-0.0.4.dist-info/WHEEL
yomikata-0.0.4.dist-info/top_level.txt
yomikata-0.0.4.dist-info/RECORD
