Metadata-Version: 2.1
Name: yomikata
Version: 0.0.4
Summary: Japanese kanji disambiguation
Author: Sam Passaglia
Project-URL: Homepage, https://github.com/passaglia/yomikata
Project-URL: Demo, https://huggingface.co/spaces/passaglia/yomikata
Project-URL: Bug Tracker, https://github.com/passaglia/yomikata/issues
Classifier: Programming Language :: Python :: 3
Classifier: Operating System :: OS Independent
Classifier: License :: OSI Approved :: MIT License
Requires-Python: >=3.8
License-File: LICENSE.md
Requires-Dist: numpy (>=1.24.0)
Requires-Dist: pandas (>=1.5.2)
Requires-Dist: jaconv (==0.3)
Requires-Dist: scikit-learn (==1.2.0)
Requires-Dist: speach (==0.1a15.post1)
Requires-Dist: torch (==1.13.1)
Requires-Dist: transformers (>=4.25.1)
Requires-Dist: datasets (==2.7.1)
Requires-Dist: pynvml (==11.4.1)
Requires-Dist: sentencepiece (==0.1.97)
Requires-Dist: rich (>=12.6.0)
Requires-Dist: black
Requires-Dist: flake8
Requires-Dist: Flake8-pyproject
Requires-Dist: isort
Requires-Dist: mlflow-skinny (==2.1.1)
Requires-Dist: pretty-errors (==1.2.25)
Requires-Dist: build
Requires-Dist: streamlit (==1.17.0)
Requires-Dist: spacy
Requires-Dist: fugashi (==1.2.1)
Requires-Dist: ipadic (==1.0.0)
Requires-Dist: jumandic (==1.0.0)
Requires-Dist: fugashi[unidic-lite]
Requires-Dist: sudachidict-full
Requires-Dist: unidic-lite
